eyecite/__init__.py
eyecite/annotate.py
eyecite/clean.py
eyecite/find.py
eyecite/helpers.py
eyecite/models.py
eyecite/py.typed
eyecite/regexes.py
eyecite/resolve.py
eyecite/test_factories.py
eyecite/tokenizers.py
eyecite/utils.py
eyecite-2.7.6.dist-info/licenses/LICENSE
eyecite-2.7.6.dist-info/METADATA
eyecite-2.7.6.dist-info/WHEEL
eyecite-2.7.6.dist-info/top_level.txt
eyecite-2.7.6.dist-info/RECORD
