Metadata-Version: 2.4
Name: eyecite
Version: 2.7.6
Summary: Tool for extracting legal citations from text strings.
Author-email: Free Law Project <info@free.law>
License-Expression: BSD-2-Clause
Project-URL: Repository, https://github.com/freelawproject/eyecite
Project-URL: Organisation Homepage, https://free.law/
Keywords: legal,courts,citations,extraction,cites
Classifier: Development Status :: 5 - Production/Stable
Classifier: Intended Audience :: Developers
Classifier: Natural Language :: English
Classifier: Operating System :: OS Independent
Classifier: Programming Language :: Python
Classifier: Programming Language :: Python :: 3
Classifier: Programming Language :: Python :: 3.10
Classifier: Programming Language :: Python :: 3.11
Classifier: Programming Language :: Python :: 3.12
Classifier: Programming Language :: Python :: Implementation :: CPython
Classifier: Programming Language :: Python :: Implementation :: PyPy
Classifier: Topic :: Software Development :: Libraries :: Python Modules
Requires-Python: >=3.10
License-File: LICENSE
Requires-Dist: courts-db>=0.10.9
Requires-Dist: fast-diff-match-patch>=2.0.0
Requires-Dist: lxml>=4.6.3
Requires-Dist: pyahocorasick>=1.2
Requires-Dist: regex>=2020.1.8
Requires-Dist: reporters-db>=3.2.53
Dynamic: license-file
